pyDataProfiling/DictionaryCollect.py
pyDataProfiling/ProfilingExecute.py
pyDataProfiling/SQLCreate.py
pyDataProfiling/__init__.py
pyDataProfiling/main.py
pyDataProfiling-0.0.2.dist-info/LICENCE
pyDataProfiling-0.0.2.dist-info/METADATA
pyDataProfiling-0.0.2.dist-info/WHEEL
pyDataProfiling-0.0.2.dist-info/top_level.txt
pyDataProfiling-0.0.2.dist-info/RECORD
