Metadata-Version: 2.1
Name: pyDataProfiling
Version: 0.0.2
Summary: Data Profiling Package(Oracle, Tibero Only)
Home-page: https://github.com/oh-seung/pyDataProfiling
Author: oh seung
Author-email: seung.oh17@gmail.com
Requires-Python: >=3.8
License-File: LICENCE
Requires-Dist: pandas (>=1.3)
Requires-Dist: numpy (>=1.20)
Requires-Dist: tqdm (>=4.62)
Requires-Dist: cx-Oracle (>=8.3.0)
Requires-Dist: pyodbc (>=4.0.32)
